LICENSE
MANIFEST.in
README.md
VERSION
build_helper.py
setup.py
tox.ini
src/zftools/__init__.py
src/zftools/fastqueue.pxd
src/zftools/fastqueue.pyx
src/zftools/metagraph.pxd
src/zftools/metagraph.pyx
src/zftools.egg-info/PKG-INFO
src/zftools.egg-info/SOURCES.txt
src/zftools.egg-info/dependency_links.txt
src/zftools.egg-info/requires.txt
src/zftools.egg-info/top_level.txt